<?xml version="1.0" encoding="utf-8"?>
<odoo>
    <data noupdate="0">
        <record id="input_deduction" model="hr.payslip.input.type">
            <field name="name">Deduction</field>
            <field name="code">DEDUCTION</field>
            <field name="country_id" eval="False"/>
        </record>

        <record id="input_reimbursement" model="hr.payslip.input.type">
            <field name="name">Reimbursement</field>
            <field name="code">REIMBURSEMENT</field>
            <field name="country_id" eval="False"/>
        </record>

        <record id="input_attachment_salary" model="hr.payslip.input.type">
            <field name="name">Attachment of Salary</field>
            <field name="code">ATTACH_SALARY</field>
            <field name="country_id" eval="False"/>
            <field name="available_in_attachments" eval="True"/>
        </record>

        <record id="input_assignment_salary" model="hr.payslip.input.type">
            <field name="name">Assignment of Salary</field>
            <field name="code">ASSIG_SALARY</field>
            <field name="country_id" eval="False"/>
            <field name="available_in_attachments" eval="True"/>
        </record>

        <record id="input_child_support" model="hr.payslip.input.type">
            <field name="name">Child Support</field>
            <field name="code">CHILD_SUPPORT</field>
            <field name="country_id" eval="False"/>
            <field name="available_in_attachments" eval="True"/>
            <field name="default_no_end_date" eval="True"/>
        </record>
    </data>
</odoo>
